guarani_coti/__init__.py
guarani_coti/main.py
guarani_coti-0.1.4.dist-info/METADATA
guarani_coti-0.1.4.dist-info/WHEEL
guarani_coti-0.1.4.dist-info/entry_points.txt
guarani_coti-0.1.4.dist-info/top_level.txt
guarani_coti-0.1.4.dist-info/RECORD
